agents/__init__.py
agents/base.py
agents/dellacherie.py
agents/q_learning.py
agents/uniform.py
auxiliary/__init__.py
auxiliary/colours.py
auxiliary/polymino.py
envs/__init__.py
envs/_simplified_tetris_base_env.py
envs/_simplified_tetris_engine.py
envs/simplified_tetris_binary_env.py
envs/simplified_tetris_heights_env.py
envs/simplified_tetris_part_binary_env.py
envs/reward_shaping/__init__.py
envs/reward_shaping/_potential_based_shaping_reward.py
envs/reward_shaping/simplified_tetris_binary_shaped_env.py
envs/reward_shaping/simplified_tetris_heights_shaped_env.py
envs/reward_shaping/simplified_tetris_part_binary_shaped_env.py
gym_simplifiedtetris-1.0.7.dist-info/LICENSE.md
gym_simplifiedtetris-1.0.7.dist-info/METADATA
gym_simplifiedtetris-1.0.7.dist-info/WHEEL
gym_simplifiedtetris-1.0.7.dist-info/top_level.txt
gym_simplifiedtetris-1.0.7.dist-info/RECORD
