Metadata-Version: 2.1
Name: gym-simplifiedtetris
Version: 1.0.7
Summary: Simplified Tetris environments compliant with OpenAI Gym's API
Home-page: https://github.com/OliverOverend/gym-simplifiedtetris
Author: Oliver Overend
Author-email: ollyoverend10@gmail.com
License: MIT
Keywords: tetris,gym,openai-gym,reinforcement-learning,research,reward-shaping
Classifier: Intended Audience :: Developers
Classifier: Intended Audience :: Education
Classifier: Intended Audience :: Science/Research
Classifier: Programming Language :: Python :: 3
Classifier: Programming Language :: Python :: 3.8
Classifier: Programming Language :: Python :: 3.9
Classifier: License :: OSI Approved :: MIT License
Classifier: Topic :: Scientific/Engineering :: Artificial Intelligence
Classifier: Topic :: Games/Entertainment :: Puzzle Games
Classifier: Topic :: Software Development :: Libraries :: Python Modules
Requires-Python: >=3.8, <3.10
License-File: LICENSE.md
Requires-Dist: absl-py (==1.3.0)
Requires-Dist: attrs (==22.1.0)
Requires-Dist: black (==22.3.0)
Requires-Dist: cachetools (==5.2.0)
Requires-Dist: certifi (==2022.9.24)
Requires-Dist: charset-normalizer (==2.1.1)
Requires-Dist: click (==8.1.3)
Requires-Dist: cloudpickle (==2.2.0)
Requires-Dist: cycler (==0.11.0)
Requires-Dist: distlib (==0.3.6)
Requires-Dist: filelock (==3.8.0)
Requires-Dist: fonttools (==4.38.0)
Requires-Dist: google-auth (==2.15.0)
Requires-Dist: google-auth-oauthlib (==0.4.6)
Requires-Dist: grpcio (==1.51.1)
Requires-Dist: gym (==0.21.0)
Requires-Dist: idna (==3.4)
Requires-Dist: importlib-metadata (==5.1.0)
Requires-Dist: iniconfig (==1.1.1)
Requires-Dist: kiwisolver (==1.4.4)
Requires-Dist: Markdown (==3.4.1)
Requires-Dist: MarkupSafe (==2.1.1)
Requires-Dist: matplotlib (==3.5.2)
Requires-Dist: mypy-extensions (==0.4.3)
Requires-Dist: numpy (==1.22.3)
Requires-Dist: oauthlib (==3.2.2)
Requires-Dist: opencv-python (==4.5.5.64)
Requires-Dist: packaging (==21.3)
Requires-Dist: pandas (==1.4.2)
Requires-Dist: pathspec (==0.10.2)
Requires-Dist: Pillow (==9.1.0)
Requires-Dist: platformdirs (==2.5.4)
Requires-Dist: pluggy (==1.0.0)
Requires-Dist: protobuf (==3.20.3)
Requires-Dist: py (==1.11.0)
Requires-Dist: pyasn1 (==0.4.8)
Requires-Dist: pyasn1-modules (==0.2.8)
Requires-Dist: pyparsing (==3.0.9)
Requires-Dist: pytest (==7.1.2)
Requires-Dist: pytest-html (==3.1.1)
Requires-Dist: pytest-metadata (==2.0.4)
Requires-Dist: python-dateutil (==2.8.2)
Requires-Dist: pytz (==2022.6)
Requires-Dist: requests (==2.28.1)
Requires-Dist: requests-oauthlib (==1.3.1)
Requires-Dist: rsa (==4.9)
Requires-Dist: six (==1.16.0)
Requires-Dist: stable-baselines3 (==1.5.0)
Requires-Dist: tensorboard (==2.11.0)
Requires-Dist: tensorboard-data-server (==0.6.1)
Requires-Dist: tensorboard-plugin-wit (==1.8.1)
Requires-Dist: toml (==0.10.2)
Requires-Dist: tomli (==2.0.1)
Requires-Dist: torch (==1.11.0)
Requires-Dist: tox (==3.25.0)
Requires-Dist: tqdm (==4.64.0)
Requires-Dist: typing-extensions (==4.4.0)
Requires-Dist: urllib3 (==1.26.13)
Requires-Dist: virtualenv (==20.17.0)
Requires-Dist: Werkzeug (==2.2.2)
Requires-Dist: zipp (==3.11.0)
